{
  "$id": "https://schema.osdu.opengroup.org/json/smds/reference-data/AbstractFacilityOperator/1",
  "$schema": "http://json-schema.org/draft-07/schema#",
  "title": "AbstractFacilityOperator",
  "description": "The organisation that was responsible for a facility at some point in time.",
  "type": "object",
  "properties": {
    "FacilityOperatorOrganisationID": {
      "description": "The company that currently operates, or previously operated the facility",
      "type": "string",
      "pattern": "srn:master-data/Organisation:[^:]+:[0-9]*"
    },
    "EffectiveDateTime": {
      "description": "The date and time at which the facility operator becomes effective.",
      "type": "string",
      "format": "date-time"
    },
    "TerminationDateTime": {
      "description": "The date and time at which the facility operator is no longer in effect.",
      "type": "string",
      "format": "date-time"
    }
  }
}